oslex2/__init__.py
oslex2-1.0.0.dist-info/METADATA
oslex2-1.0.0.dist-info/WHEEL
oslex2-1.0.0.dist-info/licenses/LICENSE
oslex2-1.0.0.dist-info/RECORD
