Metadata-Version: 2.4
Name: oslex2
Version: 1.0.0
Summary: OS-independent wrapper for shlex and mslex
Project-URL: Homepage, https://github.com/jessielw/oslex2
Project-URL: Bug Tracker, https://github.com/jessielw/oslex2/issues
Author-email: Jessie Wilson <jessielw4049@gmail.com>
License-File: LICENSE
Classifier: License :: OSI Approved :: MIT License
Classifier: Operating System :: MacOS
Classifier: Operating System :: Microsoft :: Windows
Classifier: Operating System :: POSIX
Classifier: Programming Language :: Python :: 3
Classifier: Programming Language :: Python :: 3.7
Classifier: Programming Language :: Python :: 3.8
Classifier: Programming Language :: Python :: 3.9
Classifier: Programming Language :: Python :: 3.10
Classifier: Programming Language :: Python :: 3.11
Classifier: Programming Language :: Python :: 3.12
Classifier: Programming Language :: Python :: 3.13
Requires-Python: <3.15,>=3.7
Requires-Dist: mslex>=1.3.0
